odoo10_addon_l10n_it_account-10.0.1.2.5-py3.8-nspkg.pth
odoo/addons/l10n_it_account/README.rst
odoo/addons/l10n_it_account/__init__.py
odoo/addons/l10n_it_account/__manifest__.py
odoo/addons/l10n_it_account/i18n/es_AR.po
odoo/addons/l10n_it_account/i18n/it.po
odoo/addons/l10n_it_account/i18n/l10n_it_account.pot
odoo/addons/l10n_it_account/i18n/sl.po
odoo/addons/l10n_it_account/models/__init__.py
odoo/addons/l10n_it_account/models/account_tax.py
odoo/addons/l10n_it_account/reports/account_reports_view.xml
odoo/addons/l10n_it_account/static/description/icon.png
odoo/addons/l10n_it_account/tools/__init__.py
odoo/addons/l10n_it_account/tools/account_tools.py
odoo/addons/l10n_it_account/views/account_setting.xml
odoo/addons/l10n_it_account/views/account_view.xml
odoo10_addon_l10n_it_account-10.0.1.2.5.dist-info/METADATA
odoo10_addon_l10n_it_account-10.0.1.2.5.dist-info/WHEEL
odoo10_addon_l10n_it_account-10.0.1.2.5.dist-info/namespace_packages.txt
odoo10_addon_l10n_it_account-10.0.1.2.5.dist-info/top_level.txt
odoo10_addon_l10n_it_account-10.0.1.2.5.dist-info/RECORD
