Metadata-Version: 2.1
Name: odoo10-addon-l10n-it-account
Version: 10.0.1.2.5
Summary: Italian Localization - Account
Home-page: http://www.odoo-italia.net
Author: Agile Business Group, Abstract, Odoo Community Association (OCA)
Author-email: support@odoo-community.org
License: AGPL-3
Platform: UNKNOWN
Classifier: Programming Language :: Python
Classifier: Framework :: Odoo
Classifier: Framework :: Odoo :: 10.0
Classifier: License :: OSI Approved :: GNU Affero General Public License v3
Requires-Python: ~=2.7
Requires-Dist: odoo10-addon-account-fiscal-year
Requires-Dist: odoo (<10.1dev,>=10.0)
